flask_turbo.py
setup.py
Flask_Turbo.egg-info/PKG-INFO
Flask_Turbo.egg-info/SOURCES.txt
Flask_Turbo.egg-info/dependency_links.txt
Flask_Turbo.egg-info/top_level.txt