Metadata-Version: 1.0
Name: Flask-Turbo
Version: 0.0.0
Summary: Flask-Turbo
Home-page: https://github.com/raicheff/flask-turbo
Author: Boris Raicheff
Author-email: b@raicheff.com
License: UNKNOWN
Platform: UNKNOWN
